{
  "config": {
    "wide_screen_mode": true,
    "enable_forward": true
  },
  "header": {
    "template": "green",
    "title": {
      "tag": "plain_text",
      "content": "📈 每周积分更新｜首周战报"
    },
    "subtitle": {
      "tag": "plain_text",
      "content": "榜单持续刷新中"
    }
  },
  "elements": [
    {
      "tag": "img",
      "img_key": "img_v3_0212a_484d5812-7fb5-440f-b63f-a8a35c8da7dg",
      "alt": {
        "tag": "plain_text",
        "content": "首周战报视觉头图"
      },
      "mode": "fit_horizontal",
      "compact_width": false
    },
    {
      "tag": "div",
      "text": {
        "tag": "lark_md",
        "content": "**首周战报已开启**  \nTOP3 与精选案例位正在竞争中，榜单将随数据同步更新。"
      }
    },
    {
      "tag": "hr"
    },
    {
      "tag": "div",
      "fields": [
        {
          "is_short": true,
          "text": {
            "tag": "lark_md",
            "content": "**提交数**\n首周数据统计中"
          }
        },
        {
          "is_short": true,
          "text": {
            "tag": "lark_md",
            "content": "**参与人数**\n首周数据统计中"
          }
        },
        {
          "is_short": true,
          "text": {
            "tag": "lark_md",
            "content": "**新增积分**\n首周数据统计中"
          }
        },
        {
          "is_short": true,
          "text": {
            "tag": "lark_md",
            "content": "**精选案例数**\n首周数据统计中"
          }
        }
      ]
    },
    {
      "tag": "div",
      "text": {
        "tag": "lark_md",
        "content": "**🏆 TOP3：待首周榜单产生**"
      }
    },
    {
      "tag": "note",
      "elements": [
        {
          "tag": "lark_md",
          "content": "🎯 下周挑战：每人至少提交 1 条高质量案例，冲刺群内积分增速。"
        }
      ]
    },
    {
      "tag": "action",
      "actions": [
        {
          "tag": "button",
          "text": {
            "tag": "plain_text",
            "content": "继续提交案例"
          },
          "type": "primary",
          "url": "https://detector-brother-incentives-tribute.trycloudflare.com"
        },
        {
          "tag": "button",
          "text": {
            "tag": "plain_text",
            "content": "查看活动入口"
          },
          "type": "default",
          "url": "https://detector-brother-incentives-tribute.trycloudflare.com"
        }
      ]
    }
  ]
}
